langcode_turner/__init__.py
test/__init__.py
test/unit_test.py
langcode_turner-0.1.9.dist-info/METADATA
langcode_turner-0.1.9.dist-info/WHEEL
langcode_turner-0.1.9.dist-info/top_level.txt
langcode_turner-0.1.9.dist-info/RECORD
