Metadata-Version: 2.4
Name: langcode-turner
Version: 0.1.9
Summary: langcode turn, support iso 639-1, iso 639-2, iso 639-3
Home-page: https://github.com/felikspeegel/langcode_turner
Author: Feliks Peegel
Author-email: felikspeegel@outlook.com
Classifier: Programming Language :: Python :: 3
Classifier: License :: OSI Approved :: MIT License
Requires-Python: >=3.6
Dynamic: author
Dynamic: author-email
Dynamic: classifier
Dynamic: description
Dynamic: description-content-type
Dynamic: home-page
Dynamic: requires-python
Dynamic: summary
